Workbook

Sheet Dashboard
A1: NIFTY 50 3-MIN SCALPING DASHBOARD
A3: CAPITAL MILESTONES PANEL
A4: Starting Capital | B4: ='Return on Trades & Investments'!B5 -> 40000
A5: Target Milestone(1st Year) | B5: 80000
A6: Current Active Balance | B6: =B4+B11 -> 40745
A7: Remaining to Target | B7: =MAX(0, B5-B6) -> 39255
A8: Account Growth Progress | B8: =IF(B4=0, 0, (B6-B4)/B4) -> 0.018625
A10: P&L PROGRESS TRACKER SUMMARY
A11: Total Realised Net P&L | B11: =SUM('DailyTrading Log'!P10:P100) -> 745
A12: Total Win Trades Count | B12: =COUNTIF('DailyTrading Log'!P10:P100, ">0") -> 1
A13: Total Loss Trades Count | B13: =COUNTIF('DailyTrading Log'!P10:P100, "<0") -> 0
A14: Live Strategy Win Rate | B14: =IF(COUNT('DailyTrading Log'!P10:P100)=0, 0, B12/COUNT('DailyTrading Log'!P10:P100)) -> 1
A15: Average Points per Win | B15: =IFERROR(AVERAGEIF('DailyTrading Log'!L10:L100, ">0"), 0) -> 6
A16: Average Points per Loss | B16: =IFERROR(AVERAGEIF('DailyTrading Log'!L10:L100, "<0"), 0) -> 0

Sheet DailyTrading Log
A1: NIFTY 50 TRADING LOG (2 LOTS = 130 QUANTITY)
A2: Intraday Trade Journal & Execution Log
A4: Total Net P&L | C4: Live Balance | E4: Total Trades | G4: Win Trades | I4: Loss Trades | K4: Win Rate | M4: Avg Win Pts | O4: Avg Loss Pts
A5: =SUM(P10:P100) -> 745 | C5: ='Return on Trades & Investments'!B5 + A5 -> 40745 | E5: =COUNT(P10:P100) -> 1 | G5: =COUNTIF(P10:P100, ">0") -> 1 | I5: =COUNTIF(P10:P100, "<0") -> 0 | K5: =IF(E5=0, 0, G5/E5) -> 1 | M5: =IFERROR(AVERAGEIF(L10:L100, ">0"), 0) -> 6 | O5: =IFERROR(AVERAGEIF(L10:L100, "<0"), 0) -> 0
A9: Date | B9: Time | C9: Strike | D9: Direction | E9: Qty | F9: Entry Premium | G9: SL | H9: T1 | I9: T2 | J9: T3 | K9: Exit Premium | L9: Points Caught | M9: MTM | N9: Brokerage | O9: Statutory Taxes | P9: Net P&L | Q9: Profit %
C10: NIFTY CE | D10: BUY | E10: 130 | F10: 135 | G10: 131 | H10: 141 | I10: 144 | J10: 148 | K10: 141 | L10: =IF(OR(F10="",K10=""), "", K10-F10) -> 6 | M10: =IF(L10="", "", L10*E10) -> 780 | N10: 15 | O10: 20 | P10: =IF(M10="", "", M10-(N10+O10)) -> 745 | Q10: =IF(OR(F10="",P10=""), "", P10/(F10*E10)) -> 0.042450142
E11: 130 | L11: =IF(OR(F11="",K11=""), "", K11-F11) | M11: =IF(L11="", "", L11*E11) | P11: =IF(M11="", "", M11-(N11+O11)) | Q11: =IF(OR(F11="",P11=""), "", P11/(F11*E11))
E12: 130 | L12: =IF(OR(F12="",K12=""), "", K12-F12) | M12: =IF(L12="", "", L12*E12) | P12: =IF(M12="", "", M12-(N12+O12)) | Q12: =IF(OR(F12="",P12=""), "", P12/(F12*E12))
E13: 130 | L13: =IF(OR(F13="",K13=""), "", K13-F13) | M13: =IF(L13="", "", L13*E13) | P13: =IF(M13="", "", M13-(N13+O13)) | Q13: =IF(OR(F13="",P13=""), "", P13/(F13*E13))
E14: 130 | L14: =IF(OR(F14="",K14=""), "", K14-F14) | M14: =IF(L14="", "", L14*E14) | P14: =IF(M14="", "", M14-(N14+O14)) | Q14: =IF(OR(F14="",P14=""), "", P14/(F14*E14))
E15: 130 | L15: =IF(OR(F15="",K15=""), "", K15-F15) | M15: =IF(L15="", "", L15*E15) | P15: =IF(M15="", "", M15-(N15+O15)) | Q15: =IF(OR(F15="",P15=""), "", P15/(F15*E15))
E16: 130 | L16: =IF(OR(F16="",K16=""), "", K16-F16) | M16: =IF(L16="", "", L16*E16) | P16: =IF(M16="", "", M16-(N16+O16)) | Q16: =IF(OR(F16="",P16=""), "", P16/(F16*E16))
E17: 130 | L17: =IF(OR(F17="",K17=""), "", K17-F17) | M17: =IF(L17="", "", L17*E17) | P17: =IF(M17="", "", M17-(N17+O17)) | Q17: =IF(OR(F17="",P17=""), "", P17/(F17*E17))
E18: 130 | L18: =IF(OR(F18="",K18=""), "", K18-F18) | M18: =IF(L18="", "", L18*E18) | P18: =IF(M18="", "", M18-(N18+O18)) | Q18: =IF(OR(F18="",P18=""), "", P18/(F18*E18))
E19: 130 | L19: =IF(OR(F19="",K19=""), "", K19-F19) | M19: =IF(L19="", "", L19*E19) | P19: =IF(M19="", "", M19-(N19+O19)) | Q19: =IF(OR(F19="",P19=""), "", P19/(F19*E19))
E20: 130 | L20: =IF(OR(F20="",K20=""), "", K20-F20) | M20: =IF(L20="", "", L20*E20) | P20: =IF(M20="", "", M20-(N20+O20)) | Q20: =IF(OR(F20="",P20=""), "", P20/(F20*E20))
E21: 130 | L21: =IF(OR(F21="",K21=""), "", K21-F21) | M21: =IF(L21="", "", L21*E21) | P21: =IF(M21="", "", M21-(N21+O21)) | Q21: =IF(OR(F21="",P21=""), "", P21/(F21*E21))
E22: 130 | L22: =IF(OR(F22="",K22=""), "", K22-F22) | M22: =IF(L22="", "", L22*E22) | P22: =IF(M22="", "", M22-(N22+O22)) | Q22: =IF(OR(F22="",P22=""), "", P22/(F22*E22))
... E39: 130 | L39: =IF(OR(F39="",K39=""), "", K39-F39) | M39: =IF(L39="", "", L39*E39) | P39: =IF(M39="", "", M39-(N39+O39)) | Q39: =IF(OR(F39="",P39=""), "", P39/(F39*E39))

Sheet Monthly
A1: TRADING JOURNAL (MONTHLY TRACKER)
A2: Month-End Balances, Capital Injections & Net P/L
A4: Date | B4: Balance | C4: FUND ADDED | D4: NET P/L | E4: Profit %
A5: 31-Jul-21 | B5: 14993 | C5: 0 | E5: 0
A6: 31-Aug-21 | D6: =IF(B6="", "", B6-(B5+IF(C6="",0,C6))) | E6: =IF(OR(B6="",B5=""), "", D6/B5)
A7: 30-Sep-21 | D7: =IF(B7="", "", B7-(B6+IF(C7="",0,C7))) | E7: =IF(OR(B7="",B6=""), "", D7/B6)
A8: 31-Oct-21 | D8: =IF(B8="", "", B8-(B7+IF(C8="",0,C8))) | E8: =IF(OR(B8="",B7=""), "", D8/B7)
A9: 30-Nov-21 | D9: =IF(B9="", "", B9-(B8+IF(C9="",0,C9))) | E9: =IF(OR(B9="",B8=""), "", D9/B8)
A10: 31-Dec-21 | D10: =IF(B10="", "", B10-(B9+IF(C10="",0,C10))) | E10: =IF(OR(B10="",B9=""), "", D10/B9)
A11: 31-Jan-22 | D11: =IF(B11="", "", B11-(B10+IF(C11="",0,C11))) | E11: =IF(OR(B11="",B10=""), "", D11/B10)
A12: 28-Feb-22 | D12: =IF(B12="", "", B12-(B11+IF(C12="",0,C12))) | E12: =IF(OR(B12="",B11=""), "", D12/B11)
A13: 31-Mar-22 | D13: =IF(B13="", "", B13-(B12+IF(C13="",0,C13))) | E13: =IF(OR(B13="",B12=""), "", D13/B12)
A14: 30-Apr-22 | D14: =IF(B14="", "", B14-(B13+IF(C14="",0,C14))) | E14: =IF(OR(B14="",B13=""), "", D14/B13)
A15: 31-May-22 | D15: =IF(B15="", "", B15-(B14+IF(C15="",0,C15))) | E15: =IF(OR(B15="",B14=""), "", D15/B14)
A16: 30-Jun-22 | D16: =IF(B16="", "", B16-(B15+IF(C16="",0,C16))) | E16: =IF(OR(B16="",B15=""), "", D16/B15)

Sheet Investment
A1: PORTFOLIO & ASSET ALLOCATION
A2: Investment Holdings, Platforms & Current Valuations
A4: Holdings | B4: Account name | C4: Amount invested | D4: Current value | E4: P/L | F4: Growth %
A5: Mutual Fund | B5: Paytm money | C5: 5000 | D5: 0 | E5: =D5-C5 -> -5000 | F5: =IF(C5=0, 0, E5/C5) -> -1
A6: Stocks & ETF Holdings | B6: Mstock | C6: 15000 | D6: 0 | E6: =D6-C6 -> -15000 | F6: =IF(C6=0, 0, E6/C6) -> -1
A7: Crypto | B7: CoinDCX | C7: 1500 | D7: 1800 | E7: =D7-C7 -> 300 | F7: =IF(C7=0, 0, E7/C7) -> 0.2
A8: Trading Cash | B8: Mstock | C8: 20000 | D8: 20000 | E8: =D8-C8 -> 0 | F8: =IF(C8=0, 0, E8/C8) -> 0
A9: Cash Reserve | C9: 5000 | D9: 0 | E9: =D9-C9 -> -5000 | F9: =IF(C9=0, 0, E9/C9) -> -1
A10: Closing Balance | C10: =SUM(C5:C9) -> 46500 | D10: =SUM(D5:D9) -> 21800 | E10: =SUM(E5:E9) -> -24700 | F10: =IF(C10=0, 0, E10/C10) -> -0.5311828

Sheet Return on Trades & Investments
A1: Trade & Investment Return Plan
A2: Capital Allocation & Rotation Framework
A4: Particulars | B4: Amount / Rate | C4: Formula / Rule Reference
A5: Investment Capital | B5: 40000 | C5: N (Base Capital, editable)
A6: Utilisation Capital for Rotation | B6: =B5*0.4 -> 16000 | C6: 40% of N used for rotating business activity
A7: Monthly Profit | B7: =B5*0.1 -> 4000 | C7: Monthly profit assumed at 10% of N
A8: Yearly Return from Rotation | B8: =B7*12 -> 48000 | C8: Monthly Profit × 12 months
A9: Cash Reserve | B9: =B5*0.1 -> 4000 | C9: 10% of N maintained as cash reserve
A10: Remaining Capital for Fixed Income | B10: =B5*0.5 -> 20000 | C10: Remaining 50% of N earns fixed income
A11: Fixed Yearly Income | B11: =B10*0.08 -> 1600 | C11: 8% per year on fixed capital
A12: Total Yearly Return | B12: =B8+B11 -> 49600 | C12: Yearly Rotation Return + Fixed Income
A13: Overall Yearly Return % on N | B13: =B12/B5 -> 1.24 | C13: Total Yearly Return / Investment Capital
